mohupy/__init__.py
mohupy/runtime.py
mohupy/config/__init__.py
mohupy/config/main.py
mohupy/core/__init__.py
mohupy/core/attribute.py
mohupy/core/attributeClass.py
mohupy/core/base.py
mohupy/core/constant.py
mohupy/core/construct.py
mohupy/core/funcitonClass.py
mohupy/core/function.py
mohupy/core/fuzzarray.py
mohupy/core/fuzznums.py
mohupy/core/operation.py
mohupy/core/operationClass.py
mohupy/core/operationpackage.py
mohupy/core/regedit.py
mohupy/core/operationLib/__init__.py
mohupy/core/operationLib/algebraic.py
mohupy/core/operationLib/algebraicoperation.py
mohupy/core/operationLib/einstein.py
mohupy/corelib/__init__.py
mohupy/corelib/function/__init__.py
mohupy/corelib/function/construct.py
mohupy/corelib/function/extension.py
mohupy/corelib/function/io.py
mohupy/corelib/function/math.py
mohupy/corelib/function/measure.py
mohupy/corelib/function/plot.py
mohupy/corelib/function/random.py
mohupy/corelib/function/string.py
mohupy/corelib/lib/__init__.py
mohupy/corelib/lib/base.py
mohupy/corelib/lib/classConstruct.py
mohupy/corelib/lib/classIO.py
mohupy/corelib/lib/classMeasure.py
mohupy/corelib/lib/classPlot.py
mohupy/corelib/lib/classString.py
mohupy/corelib/lib/classUtils.py
mohupy/corelib/math/__init__.py
mohupy/corelib/math/base.py
mohupy/corelib/math/classProduct.py
mohupy/corelib/math/product.py
mohupy/corelib/random/__init__.py
mohupy/corelib/random/base.py
mohupy/corelib/random/function.py
mohupy/corelib/random/randclass.py
mohupy/corelib/regedit/__init__.py
mohupy/corelib/regedit/construct.py
mohupy/corelib/regedit/distance.py
mohupy/corelib/regedit/plotlib.py
mohupy/corelib/regedit/random.py
mohupy/corelib/regedit/str2num.py
mohupy/function/__init__.py
mohupy/function/formula.py
mohupy/generator/__init__.py
mohupy/generator/membershipfunc.py
mohupy/library/__init__.py
mohupy/library/random.py
mohupy/measure/__init__.py
mohupy/measure/fuzzmeas.py
mohupy/measure/hasse.py
mohupy/measure/indices.py
mohupy/measure/integral.py
mohupy/measure/utils.py
mohupy-0.3.0.dist-info/LICENSE
mohupy-0.3.0.dist-info/METADATA
mohupy-0.3.0.dist-info/WHEEL
mohupy-0.3.0.dist-info/top_level.txt
mohupy-0.3.0.dist-info/RECORD
