Metadata-Version: 2.1
Name: mohupy
Version: 0.3.0
Summary: MohuPy is a fuzzy set calculation library, which contains fuzzy numbers, fuzzy measure, fuzzy sets and fuzzy membership functions. 
Home-page: https://github.com/yibocat/MohuPy
Author: Yibo Wang
Author-email: yibocat@yeah.net
License: MIT
Classifier: Development Status :: 4 - Beta
Classifier: License :: OSI Approved :: MIT License
Requires-Python: >=3.10
License-File: LICENSE
Requires-Dist: numpy
Requires-Dist: scipy
Requires-Dist: matplotlib
Requires-Dist: pandas
Requires-Dist: networkx
